aiorocket2/__init__.py
aiorocket2/client.py
aiorocket2/constants.py
aiorocket2/enums.py
aiorocket2/exceptions.py
aiorocket2/models.py
aiorocket2/utils.py
aiorocket2/version.py
aiorocket2/tags/__init__.py
aiorocket2/tags/app.py
aiorocket2/tags/currencies.py
aiorocket2/tags/health.py
aiorocket2/tags/multi_cheque.py
aiorocket2/tags/tg_invoices.py
aiorocket2/tags/version.py
aiorocket2/tags/withdrawal_link.py
aiorocket2-2.0.4.dist-info/LICENSE.txt
aiorocket2-2.0.4.dist-info/METADATA
aiorocket2-2.0.4.dist-info/WHEEL
aiorocket2-2.0.4.dist-info/top_level.txt
aiorocket2-2.0.4.dist-info/RECORD
