Metadata-Version: 2.1
Name: aiorocket2
Version: 2.0.4
Summary: Asynchronous Python client for xRocket API.
Author-email: RimMirK <me@rimmirk.pp.ua>
License: GNU GPLv3
Project-URL: Homepage, https://github.com/RimMirK/aiorocket2
Project-URL: Documentation, https://aiorocket2.rimmirk.pp.ua
Project-URL: Repository, https://github.com/RimMirK/aiorocket2
Project-URL: Issues, https://github.com/RimMirK/aiorocket2/issues
Keywords: crypto,telegram,async,asynchronous,payments,rocket,cryptocurrency,asyncio,crypto-bot,cryptopayments,xrocket,aiorocket,aiorocket
Classifier: Development Status :: 5 - Production/Stable
Classifier: License :: OSI Approved :: GNU General Public License v3 (GPLv3)
Classifier: Programming Language :: Python :: 3.11
Classifier: Programming Language :: Python :: 3.10
Classifier: Programming Language :: Python :: 3.9
Classifier: Programming Language :: Python :: 3.8
Classifier: Programming Language :: Python :: 3.7
Classifier: Operating System :: OS Independent
Classifier: Framework :: AsyncIO
Classifier: Typing :: Typed
Classifier: Topic :: Software Development :: Libraries :: Python Modules
Classifier: Intended Audience :: Developers
Requires-Python: >=3.7
License-File: LICENSE.txt
Requires-Dist: aiohttp
